terahertz/__init__.py
terahertz-0.1.dist-info/METADATA
terahertz-0.1.dist-info/WHEEL
terahertz-0.1.dist-info/licenses/LICENSE.txt
terahertz-0.1.dist-info/RECORD
