Metadata-Version: 2.1
Name: terahertz
Version: 0.1
Summary: Toolbox for calibration of terahertz spectra in python
Project-URL: Homepage, https://github.com/JinZhangLab/terahertz
Project-URL: Bug Tracker, https://github.com/JinZhangLab/terahertz/issues
Author-email: Jin Zhang <jinzhang@nankai.edu.cn>
License-File: LICENSE.txt
Classifier: License :: OSI Approved :: MIT License
Classifier: Operating System :: OS Independent
Classifier: Programming Language :: Python :: 3
Requires-Python: >=3.7
